cache_msi/memory.v
`timescale 1ns / 100ps

/*
 * 	File:  				ee457_mem.v
 *	Description:  		64*8 Memory
 *	Author: 			Mark Redekopp (Adapted for MSI Cache Lab)
 * 	Revisions:
 *  2009-Mar-18		Initial Release
 */
 
 module Memory 
 (
	input			[4:0]		addr,
	input	 		[15:0]  	wdata,
	input       	   			memread,
	input       	   			memwrite,
	input                       clk,
	input                       rst,
	output reg		[15:0] 		rdata,
	output   					mem_done
	);

	localparam RDWAITSTATES = 9;
	localparam WRWAITSTATES = 2;
	localparam CYCLETIME = 2;	
	parameter INIT_FILE = "datamem.txt";
	integer j;
	reg [7:0] 	mem [0:63];
	reg			WCLK;
	reg [3:0]   cnt;
	reg         running;
	reg         memread_d1;
	reg         memwrite_d1;
	initial
	begin
		for(j=0; j < 64; j=j+1)
		begin
			mem[j] = j;
		end
		$readmemh(INIT_FILE, mem);
	end

	assign mem_done = running && (cnt == 4'b0000) || memwrite;

	always @(posedge clk)
	begin
		memread_d1 <= memread;
		memwrite_d1 <= memwrite;

		if(rst)
		begin
			running <= 0;
			cnt <= 4'b0000;
		end
		if(memread && !running)
		begin
			cnt <= RDWAITSTATES;
			running <= 1;
		end
		else if(cnt > 0)
			cnt <= cnt - 1;
		else if(cnt == 0)
			running <= 0;
		
	end

	always @(posedge clk)
	begin
		if(memwrite)
		begin
			{mem[{addr, 1'b1}], mem[{addr, 1'b0}]} <= wdata;
		end
	end

	
	always @*
	begin
		if(memread && mem_done)
		begin
			rdata <= {mem[{addr, 1'b1}], mem[{addr, 1'b0}]};
		end
	end
	
endmodule

cache_msi/cache_msi.v
`timescale 1ns / 100ps

module CacheMSI (
    input             clk,
    input             reset,
    input      [ 7:0] pr_din,
    output     [ 7:0] pr_dout,
    input      [ 5:0] pr_addr,
    input             pr_rd,
    input             pr_wr,
    output            pr_done,
    input      [15:0] bus_din,
    output reg [15:0] bus_dout,
    input             bus_done_in,
    output reg        bus_done_out,
    input             bus_grant,
    output reg        bus_request,
    input      [ 4:0] bus_addr_in,
    output reg [ 4:0] bus_addr_out,
    input      [ 2:0] bus_op_in,
    output reg [ 2:0] bus_op_out
);

  localparam 	QInitial	= 		7'b0000001,
			   	QMonitor	=		7'b0000010,
				QFlush =   			7'b0000100,  
				QWB = 				7'b0001000,
			   	QBusRd	=			7'b0010000,
			   	QBusRdX	=			7'b0100000,
			   	QBusUpgr	=		7'b1000000;

  localparam BusNone = 3'b000, BusRd = 3'b001, BusUpgr = 3'b010, BusFlush = 3'b011, BusRdX = 3'b100;

  localparam I = 2'b00, S = 2'b01, M = 2'b11;


  reg     [2:0] tag                                                            [0:3];
  reg     [7:0] data                                                           [0:7];
  reg     [1:0] msi_state                                                      [0:3];
  integer       i;

  reg     [1:0] curr_msi_state;  // Dirty, Valid output of selected cache block

  reg     [8:0] state;
  wire          pr_hit;
  wire          pr_req;
  wire          bus_req;
  wire          bus_hit;

  wire    [1:0] pr_cblk;
  wire    [1:0] bus_cblk;
  wire          pr_word;
  wire    [2:0] pr_tag;
  wire    [2:0] bus_tag;
  wire    [4:0] pr_bus_addr;

  // Address breakdown
  assign pr_cblk = pr_addr[2:1];
  assign pr_word = pr_addr[0];
  assign pr_tag = pr_addr[5:3];
  assign pr_bus_addr = pr_addr[5:1];

  assign bus_cblk = bus_addr_in[1:0];
  assign bus_tag = bus_addr_in[4:2];

  assign pr_dout = data[{pr_cblk, pr_word}];

  assign pr_req = (pr_rd || pr_wr);
  assign pr_hit = (tag[pr_cblk] == pr_tag) & msi_state[pr_cblk] != I;
  assign bus_req = bus_op_in != BusNone;
  assign bus_hit = (bus_req) && (msi_state[bus_cblk] != I) && (tag[bus_cblk] == bus_tag);


  // You complete or add more signals
  assign pr_done = pr_req && pr_hit;  // Change this

  wire needToReqBus;
  assign needToReqBus = (~pr_hit) && (pr_req); // Change this: condition for when this processor needs to request use of the bus

  wire needToServiceBusRdX;
  assign needToServiceBusRdX = (bus_hit && bus_op_in == 3'b100); // Change this: condition for when this cache needs to service another's BusRdX

  wire needToServiceBusUpgr;
  assign needToServiceBusUpgr = (bus_hit && bus_op_in == 3'b010); // Change this: condition for when this cache needs to service another's BusUpgr

  // condition A on PDF diagram
  wire needToServiceBusReq;
  assign needToServiceBusReq = (bus_hit && bus_op_in == 3'b001); // Change this: condition for when we need to flush data (condition A)

  // condition B on PDF diagram
  wire startWB;
  assign startWB = ((~pr_hit) && curr_msi_state == M);  // Change this: (condition B)

  // condition C on PDF diagram   
  wire startBusRd;
  assign startBusRd = (~pr_hit) && (pr_rd);  // Change this: (condition C)

  // condition D on PDF diagram
  wire startBusRdX;
  assign startBusRdX = (~pr_hit) && (pr_wr);  // Change this: (condition D)

  // condition E on PDF diagram
  wire startBusUpgr;
  assign startBusUpgr = (pr_hit) && (pr_wr);  // Change this: (condition E)


  // pick MSI state (dirty and valid bit) from currently selected block 
  always @* begin
    if (bus_hit && bus_op_in != BusNone) curr_msi_state = {msi_state[bus_cblk]};
    else curr_msi_state = {msi_state[pr_cblk]};
  end

  // For each state consider any changes necessary to the internal and 
  // output signals:
  //   state, msi_state, tags and data
  // You can access a desired element of the tag, valid, or dirty array 
  //   by using array indexes (e.g. tag[pr_cblk]). 
  // Remember you can concatenate signals like: { data[15:8], pr_data[7:0] }
  always @(posedge clk) begin
    if (reset) begin
      state <= QInitial;
      // reqFlag <= 0;
    end else
      case (state)
        QInitial: begin
          for (i = 0; i < 4; i = i + 1) begin
            tag[i] <= 0;
            msi_state[i] <= I;
          end
          state <= QMonitor;
        end

        QMonitor: begin
          // If no bus requests then service processor requests that can
          // begin handled locally

          if (pr_hit && pr_wr) begin
            data[{pr_cblk, pr_word}] <= pr_din;
            msi_state[pr_cblk] <= M;
          end

          // Code to to invalidate a locally cached block
          if (needToServiceBusUpgr || needToServiceBusRdX) begin
            // Complete this line:  Invalidate the block
            msi_state[bus_cblk] <= I;
          end  // Code for state changes				
          else if (needToServiceBusReq) begin
            state <= QFlush;
          end else if (startWB) begin
            state <= QWB;
          end else if (!startWB && startBusRd) begin
            state <= QBusRd;
          end else if (!startWB && startBusRdX) begin
            state <= QBusRdX;
          end else if (startBusUpgr) begin
            state <= QBusUpgr;
          end

        end
        QFlush: begin
          // Update MSI state of block being flushed, appropriately

          msi_state[bus_cblk] <= S;

          // Code for state changes
          if (startWB) begin
            state <= QWB;
          end else if (!startWB && startBusRd) begin
            state <= QBusRd;
          end else if (!startWB && startBusRdX) begin
            state <= QBusRdX;
          end else if (startBusUpgr) begin
            state <= QBusUpgr;
          end else state <= QMonitor;

        end
        QWB: begin

          if (!bus_done_in) begin
            state <= QWB;
          end else if (startBusRd) begin
            state <= QBusRd;
          end else if (startBusRdX) begin
            state <= QBusRdX;
          end

        end
        QBusRd: begin

          if (!bus_done_in) begin
            state <= QBusRd;
          end else begin
            tag[pr_cblk] <= pr_tag;
            data[{pr_cblk, 1'b1}] <= bus_din[15:8];
            data[{pr_cblk, 1'b0}] <= bus_din[7:0];
            msi_state[pr_cblk] <= S;
            state <= QMonitor;
          end

        end
        QBusRdX: begin

          if (!bus_done_in) begin
            state <= QBusRdX;
          end else begin

            if (pr_word == 1'b1) begin
              data[{pr_cblk, 1'b1}] <= pr_din;
              data[{pr_cblk, 1'b0}] <= bus_din[7:0];
            end else begin
              data[{pr_cblk, 1'b1}] <= bus_din[15:8];
              data[{pr_cblk, 1'b0}] <= pr_din;
            end

            tag[pr_cblk] <= pr_tag;
            msi_state[pr_cblk] <= M;
            state <= QMonitor;
          end

        end
        QBusUpgr: begin
          state <= QMonitor;
        end
      endcase
  end


  // Output function logic
  //   Produce bus outputs:
  //     bus_request, bus_op_out, bus_dout, bus_done_out, and bus_addr_out
  always @* begin
    // Default values

    if (reset) begin
      bus_op_out <= BusNone;
      bus_addr_out <= 5'b00000;
      bus_dout <= 16'h0000;
      bus_request <= 0;
      bus_done_out <= 0;
    end else begin
      case (state)
        QMonitor: begin
          if (needToReqBus) begin
            bus_request <= 1;
          end
        end

        QFlush: begin
          if (needToReqBus) begin
            bus_request <= 1;
          end

          bus_dout <= data[bus_cblk];
          bus_addr_out <= bus_addr_in;
          bus_op_out <= 3'b011;
          bus_done_out <= 1'b1;
          // Add more code to output appropriate signals on the bus

        end

        QWB: begin

          if (bus_grant) begin
            bus_dout <= data[bus_cblk];
            bus_addr_out <= {tag[pr_cblk], pr_cblk};
            bus_op_out <= 3'b011;
            bus_done_out <= 1'b1;
          end

        end

        QBusRd: begin

          if (bus_grant) begin
            bus_addr_out <= pr_bus_addr;
            bus_op_out   <= 3'b001;
          end

        end

        QBusRdX: begin

          if (bus_grant) begin
            bus_addr_out <= pr_bus_addr;
            bus_op_out   <= 3'b100;
          end

        end

        QBusUpgr: begin

          if (bus_grant) begin
            bus_op_out   <= 3'b010;
            bus_addr_out <= pr_bus_addr;
          end

        end

      endcase
    end

  end
endmodule

cache_msi/cache_tb2.v
`timescale 1ns / 100ps

module cache_tb2;



  // Cache Inputs
  reg  [ 7:0] pr_din;
  reg  [ 5:0] pr_addr;
  reg         pr_rd;
  reg         pr_wr;

  // Bus Inputs
  reg  [ 5:0] bus_addr_in;
  reg  [ 2:0] bus_op_in;
  reg         bus_grant;
  wire [15:0] bus_din;
  wire        bus_done_in;

  // Cache Outputs 
  wire [ 7:0] pr_dout;
  wire        pr_done;

  // Bus outputs
  wire [15:0] bus_dout;
  wire        bus_done_out;
  wire        bus_request;
  wire [ 4:0] bus_addr_out;
  wire [ 2:0] bus_op_out;

  reg         clk;
  reg         rst;

  wire        stall;

  localparam 	QInitial	= 		7'b0000001,
			   	QMonitor	=		7'b0000010,
				QFlush =   			7'b0000100,  
				QWB = 				7'b0001000,
			   	QBusRd	=			7'b0010000,
			   	QBusRdX	=			7'b0100000,
			   	QBusUpgr	=		7'b1000000;
  localparam BusNone = 3'b000, BusRd = 3'b001, BusUpgr = 3'b010, BusFlush = 3'b011, BusRdX = 3'b100;

  localparam I = 2'b00, S = 2'b01, M = 2'b11;

  reg [16*8:0] state_string;
  reg [16*8:0] bus_op_out_string;
  reg [16*8:0] bus_op_in_string;

  reg [1:0] rand_cnt;
  wire mem_rd, mem_wr;
  assign mem_rd = (bus_op_out == BusRd || bus_op_out == BusRdX);
  assign mem_wr = (bus_op_out == BusFlush);

  integer i;

  // Instantiate the Unit Under Test (UUT)
  CacheMSI cache (
      .clk(clk),
      .reset(rst),
      .pr_din(pr_din),
      .pr_dout(pr_dout),
      .pr_addr(pr_addr),
      .pr_rd(pr_rd),
      .pr_wr(pr_wr),
      .pr_done(pr_done),
      .bus_din(bus_din),
      .bus_dout(bus_dout),
      .bus_done_in(bus_done_in),
      .bus_done_out(bus_done_out),
      .bus_grant(bus_grant),
      .bus_request(bus_request),
      .bus_addr_in(bus_addr_in[5:1]),
      .bus_addr_out(bus_addr_out),
      .bus_op_in(bus_op_in),
      .bus_op_out(bus_op_out)
  );


  Memory #(
      .INIT_FILE("datamem.txt")
  ) dmem (
      .addr(bus_addr_out),
      .memread(mem_rd),
      .memwrite(mem_wr),
      .wdata(bus_dout),
      .clk(clk),
      .rst(rst),
      .rdata(bus_din),
      .mem_done(bus_done_in)
  );

  always @ (cache.state) // report the state in text format in the waveform
	begin : report_state
    case (cache.state)
      QInitial: state_string = "QInitial ";
      QMonitor: state_string = "QMonitor ";
      QFlush:   state_string = "QFlush ";
      QWB:      state_string = "QWB";
      QBusRd:   state_string = "QBusRd";
      QBusRdX:  state_string = "QBusRdX";
      QBusUpgr: state_string = "QBusUpgr";
      default:  state_string = "Unknown ";

    endcase
  end

  always @ (bus_op_out) // report bus_op_out in text format in the waveform
	begin : report_bus_op_out
    case (bus_op_out)
      BusRd:    bus_op_out_string = "   BusRd   ";
      BusRdX:   bus_op_out_string = "   BusRdX  ";
      BusUpgr:  bus_op_out_string = "   BusUpgr ";
      BusFlush: bus_op_out_string = "   Flush   ";
      default:  bus_op_out_string = "   NONE    ";

    endcase
  end

  always @ (bus_op_in) // report bus_op_in in text format in the waveform
	begin : report_bus_op_in
    case (bus_op_in)
      BusRd:    bus_op_in_string = "   BusRd   ";
      BusRdX:   bus_op_in_string = "   BusRdX  ";
      BusUpgr:  bus_op_in_string = "   BusUpgr ";
      BusFlush: bus_op_in_string = "   Flush   ";
      default:  bus_op_in_string = "   NONE    ";
    endcase
  end

  always #1 clk <= ~clk;

  reg granted;

  always @(posedge clk) begin
    if (rst || rand_cnt == 2'b10) rand_cnt <= 0;
    else rand_cnt <= rand_cnt + 1;

    granted <= 0;
    if (!granted && bus_grant) granted <= 1;
    else if (granted && bus_done_out) granted <= 0;
  end
  always @* begin
    bus_grant <= 0;
    if (granted || (bus_request && rand_cnt == 0 && bus_op_in == BusNone)) bus_grant <= 1;
  end
  initial begin
    $dumpfile("cache_msi.vcd");
    $dumpvars(0, cache_tb2);
    // Initialize Inputs
    clk <= 0;
    rst <= 1;
    i   <= 0;
    #2;
    rst <= 0;
    bus_grant <= 1;
    bus_op_in <= BusNone;
    pr_rd <= 0;
    pr_wr <= 0;
    #2;

    // LW @1; 1   -> Read miss, I to S, busRd
    i <= i + 1;
    pr_addr <= 1;
    pr_rd <= 1;
    #2;
    wait (pr_done && !clk);
    wait (pr_done && clk);

    // SW 12@9;  write miss, clean, S to M, busRdX
    i <= i + 1;
    pr_addr <= 9;
    pr_rd <= 0;
    pr_wr <= 1;
    pr_din <= 12;
    wait (pr_done && !clk);
    wait (pr_done && clk);
    pr_wr <= 0;

    // Remote core bus read on Block 0 -> Not in the cache -> No action  
    i <= i + 1;
    bus_addr_in <= 0;
    bus_op_in <= BusRd;
    wait (!clk);
    wait (clk);
    wait (!clk && cache.state == QMonitor);
    wait (clk);

    bus_op_in <= BusNone;
    wait (!clk);
    wait (clk);


    // Remote core bus read on Block 8 -> mem adrress 8 & 9, M to S, FLUSH to main memory 
    i <= i + 1;  // 4
    bus_addr_in <= 8;
    bus_op_in <= BusRd;
    wait ((cache.msi_state[0] == S));
    wait (!clk);
    wait (clk);

    bus_op_in <= BusNone;
    wait (!clk);
    wait (clk);

    // SW 13@9;  write hit, S to M, busUpgr
    i <= i + 1;  // 5
    pr_addr <= 9;
    pr_rd <= 0;
    pr_wr <= 1;
    pr_din <= 13;

    wait (pr_done && !clk && (cache.msi_state[0] == M));
    wait (pr_done && clk);
    pr_wr <= 0;

    // SW 14@1; dirty write miss -> Flush, 13 -> mem[9], 1-> cache, BusRdX, M
    i <= i + 1;  // 6
    pr_addr <= 1;
    pr_rd <= 0;
    pr_wr <= 1;
    pr_din <= 14;

    wait (pr_done && !clk && (cache.msi_state[0] == M));
    wait (pr_done && clk);
    pr_wr <= 0;

    // Remote Core BusRdX on Block 8 -> Not in the cache -> No action 
    i <= i + 1;  // 7
    bus_addr_in <= 8;
    bus_op_in <= BusRdX;
    wait (!clk);
    wait (clk);
    wait (!clk && cache.state == QMonitor);
    wait (clk);
    bus_op_in <= BusNone;

    // Remote Core BusRdX on Block 0 -> mem address 0 & 1 , M to I, FLUSH
    i <= i + 1;  // 8
    bus_addr_in <= 0;
    bus_op_in <= BusRdX;
    wait ((cache.msi_state[0] == I));
    bus_op_in <= BusNone;
    wait (!clk);
    wait (clk);

    // LW @9; Clean Read miss I->S, busRd, 3 -> Cache.data
    i <= i + 1;  // 9
    pr_addr <= 9;
    pr_rd <= 1;
    pr_wr <= 0;
    wait (pr_done && !clk && (cache.msi_state[0] == S));
    wait (pr_done && clk);

    // LW @9; Hit! NONE
    i <= i + 1;  // 10
    pr_addr <= 9;
    pr_rd <= 1;
    pr_wr <= 0;
    wait (pr_done && !clk && (cache.msi_state[0] == S));
    wait (pr_done && clk);

    pr_addr <= 0;
    pr_rd <= 0;

    // Remote Core BusRdX on Block 8 -> mem address 8 & 9 , S to I
    i <= i + 1;  // 11
    bus_addr_in <= 8;
    bus_op_in <= BusRdX;
    wait ((cache.msi_state[0] == I));

    bus_op_in <= BusNone;
    wait (!clk);
    wait (clk);

    // LW @3 ; Read miss clean I->S, busRd
    i <= i + 1;  // 12
    pr_addr <= 3;
    pr_rd <= 1;
    pr_wr <= 0;
    wait (pr_done && !clk && (cache.msi_state[1] == S));
    wait (pr_done && clk);

    // LW @2 ; Hit!
    i <= i + 1;  // 13
    pr_addr <= 2;
    pr_rd <= 1;
    pr_wr <= 0;
    wait (pr_done && !clk && (cache.msi_state[1] == S));
    wait (pr_done && clk);
    pr_rd <= 0;

    // BusRd @2 ; Shared
    i <= i + 1;  // 14
    bus_addr_in <= 2;
    bus_op_in <= BusRd;
    wait (!clk);
    wait (clk);
    wait (!clk && (cache.msi_state[1] == S));
    wait (clk);
    bus_op_in <= BusNone;
    wait (!clk);
    wait (clk);

    // Remote Core busUpgr on Block 1 -> mem address 2 & 3 , S to I
    i <= i + 1;  // 15
    bus_addr_in <= 2;
    bus_op_in <= BusUpgr;
    wait (!clk && (cache.msi_state[1] == I));
    wait (clk);
    bus_op_in <= BusNone;
    wait (!clk);
    wait (clk);


    // Add your memory accesses here!


    #10 $stop();
  end

endmodule

cache_msi/cache_msi.vcd
$date
	Tue Nov  7 00:19:06 2023
$end
$version
	Icarus Verilog
$end
$timescale
	100ps
$end
$scope module cache_tb2 $end
$var wire 1 ! mem_rd $end
$var wire 8 " pr_dout [7:0] $end
$var wire 1 # pr_done $end
$var wire 1 $ mem_wr $end
$var wire 1 % bus_request $end
$var wire 3 & bus_op_out [2:0] $end
$var wire 16 ' bus_dout [15:0] $end
$var wire 1 ( bus_done_out $end
$var wire 1 ) bus_done_in $end
$var wire 16 * bus_din [15:0] $end
$var wire 5 + bus_addr_out [4:0] $end
$var reg 6 , bus_addr_in [5:0] $end
$var reg 1 - bus_grant $end
$var reg 3 . bus_op_in [2:0] $end
$var reg 129 / bus_op_in_string [128:0] $end
$var reg 129 0 bus_op_out_string [128:0] $end
$var reg 1 1 clk $end
$var reg 1 2 granted $end
$var reg 6 3 pr_addr [5:0] $end
$var reg 8 4 pr_din [7:0] $end
$var reg 1 5 pr_rd $end
$var reg 1 6 pr_wr $end
$var reg 2 7 rand_cnt [1:0] $end
$var reg 1 8 rst $end
$var reg 129 9 state_string [128:0] $end
$var integer 32 : i [31:0] $end
$scope module cache $end
$var wire 5 ; bus_addr_in [4:0] $end
$var wire 1 - bus_grant $end
$var wire 1 < bus_hit $end
$var wire 3 = bus_op_in [2:0] $end
$var wire 1 1 clk $end
$var wire 1 > needToReqBus $end
$var wire 1 ? needToServiceBusRdX $end
$var wire 1 @ needToServiceBusReq $end
$var wire 1 A needToServiceBusUpgr $end
$var wire 6 B pr_addr [5:0] $end
$var wire 8 C pr_din [7:0] $end
$var wire 1 # pr_done $end
$var wire 8 D pr_dout [7:0] $end
$var wire 1 E pr_hit $end
$var wire 1 5 pr_rd $end
$var wire 1 F pr_req $end
$var wire 1 6 pr_wr $end
$var wire 1 8 reset $end
$var wire 1 G startBusRd $end
$var wire 1 H startBusRdX $end
$var wire 1 I startBusUpgr $end
$var wire 1 J startWB $end
$var wire 1 K pr_word $end
$var wire 3 L pr_tag [2:0] $end
$var wire 2 M pr_cblk [1:0] $end
$var wire 5 N pr_bus_addr [4:0] $end
$var wire 3 O bus_tag [2:0] $end
$var wire 1 P bus_req $end
$var wire 1 ) bus_done_in $end
$var wire 16 Q bus_din [15:0] $end
$var wire 2 R bus_cblk [1:0] $end
$var reg 5 S bus_addr_out [4:0] $end
$var reg 1 ( bus_done_out $end
$var reg 16 T bus_dout [15:0] $end
$var reg 3 U bus_op_out [2:0] $end
$var reg 1 % bus_request $end
$var reg 2 V curr_msi_state [1:0] $end
$var reg 9 W state [8:0] $end
$var integer 32 X i [31:0] $end
$upscope $end
$scope module dmem $end
$var wire 5 Y addr [4:0] $end
$var wire 1 1 clk $end
$var wire 1 ) mem_done $end
$var wire 1 ! memread $end
$var wire 1 $ memwrite $end
$var wire 1 8 rst $end
$var wire 16 Z wdata [15:0] $end
$var reg 4 [ cnt [3:0] $end
$var reg 1 \ memread_d1 $end
$var reg 1 ] memwrite_d1 $end
$var reg 16 ^ rdata [15:0] $end
$var reg 1 _ running $end
$var integer 32 ` j [31:0] $end
$upscope $end
$scope begin report_bus_op_in $end
$upscope $end
$scope begin report_bus_op_out $end
$upscope $end
$scope begin report_state $end
$upscope $end
$upscope $end
$enddefinitions $end
#0
$dumpvars
b1000000 `
x_
bx ^
x]
x\
bx [
b0 Z
b0 Y
bx X
bx W
bx V
b0 U
b0 T
b0 S
bx R
bx Q
xP
bx O
bx N
bx M
bx L
xK
xJ
xI
xH
xG
xF
xE
bx D
bx C
bx B
xA
x@
x?
x>
bx =
x<
bx ;
b0 :
bx 9
18
bx 7
x6
x5
bx 4
bx 3
x2
01
b10000000100000001000000100111001001111010011100100010100100000001000000010000000100000 0
bx /
bx .
0-
bx ,
b0 +
bx *
x)
0(
b0 '
b0 &
0%
0$
x#
bx "
0!
$end
#10
0)
b10100010100100101101110011010010111010001101001011000010110110000100000 9
b1 W
b0 [
0_
0]
0\
02
b0 7
11
#20
0#
0>
0<
0H
0I
0F
0G
0?
0A
0@
b10000000100000001000000100111001001111010011100100010100100000001000000010000000100000 /
01
06
05
0P
b0 .
b0 =
0-
08
#30
b10100010100110101101111011011100110100101110100011011110111001000100000 9
b1 7
b10 W
b100 X
11
#40
1%
0J
1>
0E
b0 V
1F
1G
b0 M
1K
b0 L
b0 N
01
15
b1 3
b1 B
b1 :
#50
b10100010100001001110101011100110101001001100100 9
b10000 W
b10 7
11
#60
01
#70
1!
b10000000100000001000000100001001110101011100110101001001100100001000000010000000100000 0
b1 &
b1 U
1-
b0 7
11
#80
01
#90
1-
1_
b1001 [
1\
12
b1 7
11
#100
01
#110
0-
02
b10 7
b1000 [
11
#120
01
#130
1-
b111 [
b0 7
11
#140
01
#150
1-
12
b1 7
b110 [
11
#160
01
#170
0-
b101 [
02
b10 7
11
#180
01
#190
1-
b0 7
b100 [
11
#200
01
#210
1-
b11 [
12
b1 7
11
#220
01
#230
0-
02
b10 7
b10 [
11
#240
01
#250
1-
b1 [
b0 7
11
#260
01
#270
b100000000 *
b100000000 Q
b100000000 ^
1-
1)
12
b1 7
b0 [
11
#280
01
#290
0-
0>
0G
1#
0)
b10100010100110101101111011011100110100101110100011011110111001000100000 9
1E
b1 V
b10 W
b1 "
b1 D
0_
02
b10 7
11
#300
01
#310
1-
1>
1H
0#
0E
0I
b1 L
b100 N
b0 7
1_
b1001 [
b1100 4
b1100 C
16
05
b1001 3
b1001 B
b10 :
11
#320
01
#330
b10000000100000001000000100001001110101011100110101001001100100010110000010000000100000 0
b100 &
b100 U
b100 +
b100 S
b100 Y
1-
b1010001010000100111010101110011010100100110010001011000 9
b100000 W
b1000 [
12
b1 7
11
#340
01
#350
0-
02
b10 7
b111 [
11
#360
01
#370
1-
b110 [
b0 7
11
#380
01
#390
1-
12
b1 7
b101 [
11
#400
01
#410
0-
b100 [
02
b10 7
11
#420
01
#430
1-
b0 7
b11 [
11
#440
01
#450
1-
b10 [
12
b1 7
11
#460
01
#470
0-
02
b10 7
b1 [
11
#480
01
#490
b100100001000 *
b100100001000 Q
b100100001000 ^
1-
1)
b0 [
b0 7
11
#500
01
#510
1-
0>
0H
0)
1#
1I
b10100010100110101101111011011100110100101110100011011110111001000100000 9
b11 V
1E
12
b1 7
0_
b10 W
b1100 "
b1100 D
11
#520
01
#530
0!
b10000000100000001000000100001001110101011100110101010101110000011001110111001000100000 0
b10 &
b10 U
0-
b0 R
b0 O
0#
b101000101000010011101010111001101010101011100000110011101110010 9
b10000000100000001000000100001001110101011100110101001001100100001000000010000000100000 /
b0 ;
0F
0I
b1000000 W
1_
b1001 [
02
b10 7
1P
b1 .
b1 =
b0 ,
b11 :
06
11
#540
01
#550
b10100010100110101101111011011100110100101110100011011110111001000100000 9
b0 7
b1000 [
0\
b10 W
11
#560
01
#570
b10000000100000001000000100111001001111010011100100010100100000001000000010000000100000 /
b111 [
b1 7
0P
b0 .
b0 =
11
#580
01
#590
1@
1<
b1 O
b10000000100000001000000100001001110101011100110101001001100100001000000010000000100000 /
b100 ;
b10 7
b110 [
1P
b1 .
b1 =
b1000 ,
b100 :
11
#600
01
#610
1)
b10000000100000001000000100011001101100011101010111001101101000001000000010000000100000 0
1(
1$
b11 &
b11 U
b1000 '
b1000 T
b1000 Z
b1010001010001100110110001110101011100110110100000100000 9
b100 W
b101 [
b0 7
11
#620
01
#630
b10100010100110101101111011011100110100101110100011011110111001000100000 9
b1 V
b1 7
b100 [
1]
b10 W
11
#640
01
#650
0<
b1010001010001100110110001110101011100110110100000100000 9
0@
b10000000100000001000000100111001001111010011100100010100100000001000000010000000100000 /
b100 W
b11 [
b10 7
0P
b0 .
b0 =
11
#660
01
#670
1-
1#
b10100010100110101101111011011100110100101110100011011110111001000100000 9
1F
1I
b0 7
b10 [
b10 W
b1101 4
b1101 C
16
b101 :
11
#680
01
#690
0)
b10000000100000001000000100001001110101011100110101010101110000011001110111001000100000 0
0$
b10 &
b10 U
1-
b101000101000010011101010111001101010101011100000110011101110010 9
b11 V
b1000000 W
b1101 "
b1101 D
b1 [
12
b1 7
11
#700
01
#710
0-
1>
1J
1H
0#
0I
1)
0E
b10100010100110101101111011011100110100101110100011011110111001000100000 9
b0 L
b0 N
02
b10 7
b0 [
0]
b10 W
b1110 4
b1110 C
b1 3
b1 B
b110 :
16
11
#720
01
#730
b10000000100000001000000100011001101100011101010111001101101000001000000010000000100000 0
1$
b11 &
b11 U
1-
1)
b10100010101011101000010 9
b1000 W
0_
b0 7
11
#740
01
#750
0)
1!
b10000000100000001000000100001001110101011100110101001001100100010110000010000000100000 0
1-
0$
b100 &
b100 U
b0 +
b0 S
b0 Y
b1010001010000100111010101110011010100100110010001011000 9
12
b1 7
1]
b100000 W
11
#760
01
#770
0-
1_
b1001 [
0]
1\
02
b10 7
11
#780
01
#790
1-
b0 7
b1000 [
11
#800
01
#810
1-
b111 [
12
b1 7
11
#820
01
#830
0-
02
b10 7
b110 [
11
#840
01
#850
1-
b101 [
b0 7
11
#860
01
#870
1-
12
b1 7
b100 [
11
#880
01
#890
0-
b11 [
02
b10 7
11
#900
01
#910
1-
b0 7
b10 [
11
#920
01
#930
1-
b1 [
12
b1 7
11
#940
01
#950
b100000000 *
b100000000 Q
b100000000 ^
0-
1)
02
b10 7
b0 [
11
#960
01
#970
1-
0>
0J
0H
1#
1I
0)
b10100010100110101101111011011100110100101110100011011110111001000100000 9
1E
b10 W
b1110 "
b1110 D
0_
b0 7
11
#980
01
#990
0!
b10000000100000001000000100001001110101011100110101010101110000011001110111001000100000 0
b10 &
b10 U
1-
0#
b101000101000010011101010111001101010101011100000110011101110010 9
b10000000100000001000000100001001110101011100110101001001100100010110000010000000100000 /
0F
0I
12
b1 7
1_
b1001 [
b1000000 W
1P
b100 .
b100 =
b111 :
06
11
#1000
01
#1010
0-
b10100010100110101101111011011100110100101110100011011110111001000100000 9
b10 W
b1000 [
0\
02
b10 7
11
#1020
01
#1030
1?
1<
b0 O
b0 ;
b0 7
b111 [
b0 ,
b1000 :
1P
b100 .
b100 =
11
#1040
01
#1050
b10000000100000001000000100111001001111010011100100010100100000001000000010000000100000 /
0P
b0 .
b0 =
0?
0<
0E
b0 V
b110 [
b1 7
11
#1060
01
#1070
1>
1F
1G
b1 L
b100 N
b10 7
b101 [
15
b1001 3
b1001 B
b1001 :
11
#1080
01
#1090
1!
b10000000100000001000000100001001110101011100110101001001100100001000000010000000100000 0
b1 &
b1 U
b100 +
b100 S
b100 Y
1-
b10100010100001001110101011100110101001001100100 9
b10000 W
b100 [
b0 7
11
#1100
01
#1110
1-
12
b1 7
b11 [
1\
11
#1120
01
#1130
0-
b10 [
02
b10 7
11
#1140
01
#1150
1-
b0 7
b1 [
11
#1160
01
#1170
b1000 *
b1000 Q
b1000 ^
1-
1)
b0 [
12
b1 7
11
#1180
01
#1190
0-
0>
0G
0)
1#
b10100010100110101101111011011100110100101110100011011110111001000100000 9
b1 V
1E
02
b10 7
0_
b10 W
b0 "
b0 D
11
#1200
01
#1210
1-
1_
b1001 [
b0 7
b1010 :
11
#1220
01
#1230
1-
1?
1<
b1 O
0#
0E
b10000000100000001000000100001001110101011100110101001001100100010110000010000000100000 /
b100 ;
0F
b1000 "
b1000 D
0K
b0 L
b0 N
12
b1 7
b1000 [
1P
b100 .
b100 =
b1000 ,
b1011 :
05
b0 3
b0 B
11
#1240
01
#1250
b10000000100000001000000100111001001111010011100100010100100000001000000010000000100000 /
0P
b0 .
b0 =
0-
0?
0<
b0 V
b111 [
02
b10 7
11
#1260
01
#1270
1-
1>
1F
1G
b1 M
bx "
bx D
1K
b1 N
b0 7
b110 [
15
b11 3
b11 B
b1100 :
11
#1280
01
#1290
b1 +
b1 S
b1 Y
1-
b10100010100001001110101011100110101001001100100 9
b10000 W
b101 [
12
b1 7
11
#1300
01
#1310
0-
02
b10 7
b100 [
11
#1320
01
#1330
1-
b11 [
b0 7
11
#1340
01
#1350
1-
12
b1 7
b10 [
11
#1360
01
#1370
0-
b1 [
02
b10 7
11
#1380
01
#1390
b1100000010 *
b1100000010 Q
b1100000010 ^
1-
1)
b0 7
b0 [
11
#1400
01
#1410
1-
0>
0G
1#
0)
b10100010100110101101111011011100110100101110100011011110111001000100000 9
1E
b1 V
b10 W
b11 "
b11 D
0_
12
b1 7
11
#1420
01
#1430
0-
b10 "
b10 D
0K
02
b10 7
1_
b1001 [
b10 3
b10 B
b1101 :
11
#1440
01
#1450
1@
1<
b1 R
b0 O
0#
b10000000100000001000000100001001110101011100110101001001100100001000000010000000100000 /
b1 ;
0F
b1000 [
b0 7
1P
b1 .
b1 =
b10 ,
b1110 :
05
11
#1460
01
