cache/memory.v
`timescale 1ns / 100ps

/*
 * 	File:  				ee457_mem.v
 *	Description:  		64*8 Memory
 *	Author: 			Mark Redekopp (Adopted for MSI Cache Lab)
 * 	Revisions:
 *  2009-Mar-18		Initial Release
 */
 
 module Memory 
 (
	input			[4:0]		addr,
	input	 		[15:0]  	wdata,
	input       	   			memread,
	input       	   			memwrite,
	input                       clk,
	input                       rst,
	output reg		[15:0] 		rdata,
	output   					mem_done
	);

	localparam WAITSTATES = 9;
	localparam CYCLETIME = 2;	
	parameter INIT_FILE = "mem_file.txt";

	reg [7:0] 	mem [0:63];
	reg			WCLK;
	reg [3:0]   cnt;
	reg         running;
	reg         memread_d1;
	reg         memwrite_d1;
	integer     j;
	
	initial
	begin
		for(j=0; j < 64; j=j+1)
		begin
			mem[j] = j;
		end
		$readmemh(INIT_FILE, mem);
	end

	assign mem_done = running && (cnt == 4'b0000);

	always @(posedge clk)
	begin
		memread_d1 <= memread;
		memwrite_d1 <= memwrite;

		if(rst)
		begin
			running <= 0;
			cnt <= 4'b0000;
		end
		if((memread || memwrite) && !running)
		begin
			cnt <= WAITSTATES;
			running <= 1;
		end
		else if(cnt > 0)
			cnt <= cnt - 1;
		else if(cnt == 0)
			running <= 0;
		
	end

	always @(clk)
	begin
		if(memwrite && mem_done)
		begin
			{mem[{addr, 1'b1}], mem[{addr, 1'b0}]} <= wdata;
		end
	end

	
	always @*
	begin
		if(memread && mem_done)
		begin
			rdata <= {mem[{addr, 1'b1}], mem[{addr, 1'b0}]};
		end
	end
	
endmodule

cache/cache_p1.v

`timescale 1ns / 1ns
module Cache (
    input             clk,
    input             reset,
    input      [ 7:0] pr_din,
    output     [ 7:0] pr_dout,
    input      [ 5:0] pr_addr,
    input             pr_rd,
    input             pr_wr,
    output            pr_done,
    input      [15:0] bus_din,
    output reg [15:0] bus_dout,
    input             bus_done,
    output reg        bus_rd,
    output reg        bus_wr,
    output reg [ 4:0] bus_addr,
    output     [ 2:0] temp,
    output            pr_tag_eq,
    output reg        in_side
);

  reg     [2:0] tag         [0:3];
  reg     [7:0] data        [0:7];
  reg     [3:0] valid;
  reg     [3:0] dirty;
  integer       i;

  reg     [3:0] state;
  wire          hit;
  wire    [1:0] pr_cblk;
  wire          pr_word;
  wire    [2:0] pr_tag;
  wire    [4:0] pr_bus_addr;


  // Address breakdown
  assign pr_cblk = pr_addr[2:1];
  assign pr_word = pr_addr[0];
  assign pr_tag = pr_addr[5:3];
  assign pr_bus_addr = pr_addr[5:1];

  localparam QInitial = 4'b0001, QMonitor = 4'b0010, QWB = 4'b0100, QFetch = 4'b1000;
	
  // Completed...You may change if needed but we recommend keeping this
  assign req = (pr_rd || pr_wr);
  assign pr_done = req & hit;
  assign temp = tag[pr_cblk];

  assign pr_tag_eq = tag[pr_cblk] == pr_tag;


  // You complete (change the assignments below to the appropriate logic)
  assign hit = (pr_tag == tag[pr_cblk]) && (valid[pr_cblk] == 1'b1);
  assign pr_dout = data[{pr_cblk, pr_word}];

  // For each state consider any changes necessary to the registered signals:
  //   state, valid and dirty bits, tags and data
  // You can access a desired element of the tag, valid, or dirty array by  
  //   using array indexes (e.g. tag[pr_cblk]). 
  // Remember you can concatenate signals like:  { data[15:8], pr_data[7:0] } 
  always @(posedge clk) begin
    if (reset) state <= QInitial;
    else
      case (state)
        QInitial: begin
          valid <= 4'b0000;
          dirty <= 4'b0000;
          for (i = 0; i < 4; i = i + 1) tag[i] <= 0;

          state <= QMonitor;
        end
        QMonitor: begin

          if ((pr_tag == tag[pr_cblk]) && (valid[pr_cblk] == 1'b1) && pr_wr) begin

            in_side <= 1'b1;
            data[{pr_cblk, pr_word}] <= pr_din;
            dirty[pr_cblk] <= 1'b1;

          end else if (!hit) begin

            in_side <= 1'b0;
            if (dirty[pr_cblk] == 1'b1) begin
              state <= QWB;
            end else begin
              state <= QFetch;
            end

          end else begin
            state   <= QMonitor;
            in_side <= 1'b0;
          end


        end
        // Hint: you only need to update signals when the WB is complete 
        QWB: begin

          in_side <= 1'b0;

          if (bus_done == 1'b1) begin
            state <= QFetch;
          end else begin
            state <= QWB;
          end

        end

        // Hint: you only need to update signals when the fetch is complete 
        QFetch: begin

          in_side <= 1'b0;

          if (bus_done == 1'b1) begin

            state <= QMonitor;
            tag[pr_cblk] <= pr_tag;
            valid[pr_cblk] <= 1'b1;

            if (pr_wr) begin
              dirty[pr_cblk] <= 1'b1;

              if (pr_word == 1'b0) begin
                data[{pr_cblk, 1'b0}] <= pr_din;
                data[{pr_cblk, 1'b1}] <= bus_din[15:8];
              end else begin
                data[{pr_cblk, 1'b0}] <= bus_din[7:0];
                data[{pr_cblk, 1'b1}] <= pr_din;
              end

            end else if (pr_rd) begin

              dirty[pr_cblk] <= 1'b0;
              data[{pr_cblk, 1'b0}] <= bus_din[7:0];
              data[{pr_cblk, 1'b1}] <= bus_din[15:8];

            end

          end else begin
            state <= QFetch;
          end

        end

      endcase
  end

  // Output Function Logic
  // Produce the bus/memory signals:
  //    bus_rd, bus_wr, bus_dout, and bus_addr
  always @* begin
    case (state)
      QInitial: begin
        bus_rd   <= 0;
        bus_wr   <= 0;
        bus_addr <= 5'b0;
        bus_dout <= 16'b0;
      end

      QMonitor: begin

        bus_rd <= 1'b0;
        bus_wr <= 1'b0;

      end

      QWB: begin

        bus_rd   <= 1'b0;
        bus_wr   <= 1'b1;
        bus_addr <= {tag[pr_cblk], pr_cblk};
        bus_dout <= {data[{pr_cblk, 1'b1}], data[{pr_cblk, 1'b0}]};

      end
      QFetch: begin

        bus_rd   <= 1'b1;
        bus_wr   <= 1'b0;
        bus_addr <= pr_bus_addr;

      end
    endcase
  end
endmodule

cache/cache_tb1.v
`timescale 1ns / 1ns

module cache_tb;

  // Cache Inputs
  reg  [ 7:0] pr_din;
  reg  [ 5:0] pr_addr;
  reg         pr_rd;
  reg         pr_wr;


  reg         clk;
  reg         rst;
  wire        pr_tag_eq;
  wire        in_side;


  // Cache Outputs and memory inputs

  wire        pr_done;
  wire [ 7:0] pr_dout;
  wire [15:0] bus_dout;
  wire        bus_rd;
  wire        bus_wr;
  wire [ 4:0] bus_addr;

  // bus output
  wire [15:0] bus_din;
  wire        bus_done;
  wire [ 2:0] temp;

  localparam QInitial = 4'b0001, QMonitor = 4'b0010, QWB = 4'b0100, QFetch = 4'b1000;
  localparam CYCLETIME = 2;
  reg [16*8:0] state_string;

  // Instantiate the Unit Under Test (UUT)
  Cache cache (
      .clk(clk),
      .reset(rst),
      .pr_dout(pr_dout),
      .pr_din(pr_din),
      .pr_addr(pr_addr),
      .pr_rd(pr_rd),
      .pr_wr(pr_wr),
      .pr_done(pr_done),
      .bus_dout(bus_dout),
      .bus_din(bus_din),
      .bus_done(bus_done),
      .bus_rd(bus_rd),
      .bus_wr(bus_wr),
      .bus_addr(bus_addr),
      .temp(temp),
      .pr_tag_eq(pr_tag_eq),
      .in_side(in_side)
  );

  Memory #(
      .INIT_FILE("datamem.txt")
  ) dmem (
      .addr(bus_addr),
      .memread(bus_rd),
      .memwrite(bus_wr),
      .wdata(bus_dout),
      .clk(clk),
      .rst(rst),
      .rdata(bus_din),
      .mem_done(bus_done)
  );

  always @ (cache.state) // report the state in text format in the waveform
	begin : report_state
    case (cache.state)
      QInitial: state_string = "  QInitial     ";
      QMonitor: state_string = "  QMonitor     ";
      QWB:      state_string = "  QWB          ";
      QFetch:   state_string = "  QFetch       ";
      default:  state_string = "  Unknown	  ";

    endcase
  end

  always #1 clk = ~clk;

  initial begin

    $dumpfile("cache.vcd");
    $dumpvars(0, cache_tb);
    // Initialize Inputs
    clk = 0;
    rst = 1;
    #CYCLETIME;
    rst = 0;
    #CYCLETIME;

    // LW @1; 1
    pr_din  = 8'bzzzzzzzz;
    pr_addr = 1;
    pr_rd   = 1;
    //CYCLETIME;

    wait (pr_done && !clk);
    wait (pr_done && clk);
    wait (pr_dout == 8'h01);
    wait (cache.data[0] == 8'h00);
    wait (cache.data[1] == 8'h01);

    pr_rd = 0;
    pr_wr = 0;

    #2;

    // SW 12@9;  
    pr_addr = 9;
    pr_rd   = 0;
    pr_wr   = 1;
    pr_din  = 12;
    //#CYCLETIME;

    wait (pr_done && !clk);
    wait (pr_done && clk);
    wait (cache.data[0] == 8'h08);
    wait (cache.data[1] == 8'h0c);

    pr_rd = 0;
    pr_wr = 0;

    #2;

    // SW 13@9;
    pr_addr = 9;
    pr_rd   = 0;
    pr_wr   = 1;
    pr_din  = 13;
    //#CYCLETIME;


    wait (pr_done && !clk);
    wait (pr_done && clk);
    wait (cache.data[0] == 8'h08);
    wait (cache.data[1] == 8'h0d);

    pr_rd = 0;
    pr_wr = 0;

    #2;

    // SW 14@1; WB 13-> mem[9], 4-> cache
    pr_addr = 1;
    pr_rd   = 0;
    pr_wr   = 1;
    pr_din  = 14;
    //#CYCLETIME;

    wait (pr_done && !clk);
    wait (pr_done && clk);
    wait (cache.data[0] == 8'h00);
    wait (cache.data[1] == 8'h0e);

    pr_rd = 0;
    pr_wr = 0;

    #2;

    // LW @9; WB 14-> mem[1], mem[9]=13 -> Cache  
    pr_din  = 8'bzzzzzzzz;
    pr_addr = 9;
    pr_rd   = 1;
    pr_wr   = 0;
    //#CYCLETIME;

    wait (pr_done && !clk);
    wait (pr_done && clk);
    wait (cache.data[0] == 8'h08);
    wait (cache.data[1] == 8'h0d);
    wait (pr_dout == 8'h0d);

    pr_rd = 0;
    pr_wr = 0;

    #2;


    // LW @8; Hit!
    pr_din  = 8'bzzzzzzzz;
    pr_addr = 8;
    pr_rd   = 1;
    pr_wr   = 0;
    //#CYCLETIME;

    wait (pr_done && !clk);
    wait (pr_done && clk);
    wait (pr_dout == 8'h08);

    pr_rd = 0;
    pr_wr = 0;

    #2;


    // SW 17@4 ; Miss
    pr_addr = 4;
    pr_rd   = 0;
    pr_wr   = 1;
    pr_din  = 17;
    //#CYCLETIME;

    wait (pr_done && !clk);
    wait (pr_done && clk);
    wait (cache.data[4] == 8'h11);
    wait (cache.data[5] == 8'h05);

    pr_rd = 0;
    pr_wr = 0;

    #2;

    // LW @9 ; Hit
    pr_din  = 8'bzzzzzzzz;
    pr_addr = 9;
    pr_rd   = 1;
    pr_wr   = 0;
    //#CYCLETIME;

    wait (pr_done && !clk);
    wait (pr_done && clk);
    wait (pr_dout == 8'h0d);

    // LW @13 ; WB 17->mem[4], mem[13] -> Cache
    pr_din  = 8'bzzzzzzzz;
    pr_addr = 13;
    pr_rd   = 1;
    pr_wr   = 0;
    //#CYCLETIME;

    wait (pr_done && !clk);
    wait (pr_done && clk);
    wait (cache.data[4] == 8'h0c);
    wait (cache.data[5] == 8'h0d);
    wait (pr_dout == 8'h0d);

    pr_din = 8'bzzzzzzzz;
    pr_rd  = 0;
    pr_wr  = 0;


    #10;
    $stop();
  end

endmodule

cache/cache.vcd
$date
	Mon Nov  6 10:29:28 2023
$end
$version
	Icarus Verilog
$end
$timescale
	100ps
$end
$scope module cache_tb $end
$var wire 3 ! temp [2:0] $end
$var wire 1 " pr_tag_eq $end
$var wire 8 # pr_dout [7:0] $end
$var wire 1 $ pr_done $end
$var wire 1 % in_side $end
$var wire 1 & bus_wr $end
$var wire 1 ' bus_rd $end
$var wire 16 ( bus_dout [15:0] $end
$var wire 1 ) bus_done $end
$var wire 16 * bus_din [15:0] $end
$var wire 5 + bus_addr [4:0] $end
$var reg 1 , clk $end
$var reg 6 - pr_addr [5:0] $end
$var reg 8 . pr_din [7:0] $end
$var reg 1 / pr_rd $end
$var reg 1 0 pr_wr $end
$var reg 1 1 rst $end
$var reg 129 2 state_string [128:0] $end
$scope module cache $end
$var wire 1 , clk $end
$var wire 1 3 hit $end
$var wire 6 4 pr_addr [5:0] $end
$var wire 8 5 pr_din [7:0] $end
$var wire 1 $ pr_done $end
$var wire 8 6 pr_dout [7:0] $end
$var wire 1 / pr_rd $end
$var wire 1 0 pr_wr $end
$var wire 1 7 req $end
$var wire 1 1 reset $end
$var wire 3 8 temp [2:0] $end
$var wire 1 9 pr_word $end
$var wire 1 " pr_tag_eq $end
$var wire 3 : pr_tag [2:0] $end
$var wire 2 ; pr_cblk [1:0] $end
$var wire 5 < pr_bus_addr [4:0] $end
$var wire 1 ) bus_done $end
$var wire 16 = bus_din [15:0] $end
$var reg 5 > bus_addr [4:0] $end
$var reg 16 ? bus_dout [15:0] $end
$var reg 1 ' bus_rd $end
$var reg 1 & bus_wr $end
$var reg 4 @ dirty [3:0] $end
$var reg 1 % in_side $end
$var reg 4 A state [3:0] $end
$var reg 4 B valid [3:0] $end
$var integer 32 C i [31:0] $end
$upscope $end
$scope module dmem $end
$var wire 5 D addr [4:0] $end
$var wire 1 , clk $end
$var wire 1 ) mem_done $end
$var wire 1 ' memread $end
$var wire 1 & memwrite $end
$var wire 1 1 rst $end
$var wire 16 E wdata [15:0] $end
$var reg 4 F cnt [3:0] $end
$var reg 1 G memread_d1 $end
$var reg 1 H memwrite_d1 $end
$var reg 16 I rdata [15:0] $end
$var reg 1 J running $end
$var integer 32 K j [31:0] $end
$upscope $end
$scope begin report_state $end
$upscope $end
$upscope $end
$enddefinitions $end
#0
$dumpvars
b1000000 K
xJ
bx I
xH
xG
bx F
bx E
bx D
bx C
bx B
bx A
bx @
bx ?
bx >
bx =
bx <
bx ;
bx :
x9
bx 8
x7
bx 6
bx 5
bx 4
x3
bx 2
11
x0
x/
bx .
bx -
0,
bx +
bx *
x)
bx (
x'
x&
x%
x$
bx #
x"
bx !
$end
#10
b0 (
b0 ?
b0 E
b0 +
b0 >
b0 D
0&
0'
b1000000010000001010001010010010110111001101001011101000110100101100001011011000010000000100000001000000010000000100000 2
0)
b1 A
b0 F
0J
1,
#20
0,
01
#30
b1000000010000001010001010011010110111101101110011010010111010001101111011100100010000000100000001000000010000000100000 2
0H
0G
b10 A
b0 @
b0 B
b100 C
1,
#40
0$
03
17
b0 !
b0 8
1"
b0 ;
19
b0 :
b0 <
0,
1/
b1 -
b1 4
bz .
bz 5
#50
1'
b1000000010000001010001010001100110010101110100011000110110100000100000001000000010000000100000001000000010000000100000 2
b1000 A
0%
1,
#60
0,
#70
1J
b1001 F
1G
1,
#80
0,
#90
b1000 F
1,
#100
0,
#110
b111 F
1,
#120
0,
#130
b110 F
1,
#140
0,
#150
b101 F
1,
#160
0,
#170
b100 F
1,
#180
0,
#190
b11 F
1,
#200
0,
#210
b10 F
1,
#220
0,
#230
b1 F
1,
#240
0,
#250
b100000000 *
b100000000 =
b100000000 I
1)
b0 F
1,
#260
0,
#270
0'
1$
13
0)
b1000000010000001010001010011010110111101101110011010010111010001101111011100100010000000100000001000000010000000100000 2
0J
b1 #
b1 6
b1 B
b10 A
1,
#280
0,
#290
0G
0$
07
00
0/
1,
#300
0,
#310
03
17
0"
b1 :
b100 <
1,
b1100 .
b1100 5
10
b1001 -
b1001 4
#320
0,
#330
b100 +
b100 >
b100 D
1'
b1000000010000001010001010001100110010101110100011000110110100000100000001000000010000000100000001000000010000000100000 2
b1000 A
1,
#340
0,
#350
1J
b1001 F
1G
1,
#360
0,
#370
b1000 F
1,
#380
0,
#390
b111 F
1,
#400
0,
#410
b110 F
1,
#420
0,
#430
b101 F
1,
#440
0,
#450
b100 F
1,
#460
0,
#470
b11 F
1,
#480
0,
#490
b10 F
1,
#500
0,
#510
b1 F
1,
#520
0,
#530
b100100001000 *
b100100001000 =
b100100001000 I
1)
b0 F
1,
#540
0,
#550
0'
1$
0)
13
b1000000010000001010001010011010110111101101110011010010111010001101111011100100010000000100000001000000010000000100000 2
0J
b1100 #
b1100 6
b1 @
b1 !
b1 8
1"
b10 A
1,
#560
0,
#570
0G
0$
07
00
1,
#580
0,
#590
b1101 #
b1101 6
1%
1$
17
1,
b1101 .
b1101 5
10
#600
0,
#610
0%
0$
07
00
1,
#620
0,
#630
03
17
0"
b0 :
b0 <
1,
b1110 .
b1110 5
10
b1 -
b1 4
#640
0,
#650
b110100001000 (
b110100001000 ?
b110100001000 E
1&
b1000000010000001010001010101110100001000100000001000000010000000100000001000000010000000100000001000000010000000100000 2
b100 A
1,
#660
0,
#670
1J
b1001 F
1H
1,
#680
0,
#690
b1000 F
1,
#700
0,
#710
b111 F
1,
#720
0,
#730
b110 F
1,
#740
0,
#750
b101 F
1,
#760
0,
#770
b100 F
1,
#780
0,
#790
b11 F
1,
#800
0,
#810
b10 F
1,
#820
0,
#830
b1 F
1,
#840
0,
#850
1)
b0 F
1,
#860
0,
#870
b0 +
b0 >
b0 D
0&
1'
0)
b1000000010000001010001010001100110010101110100011000110110100000100000001000000010000000100000001000000010000000100000 2
0J
b1000 A
1,
#880
0,
#890
1J
b1001 F
0H
1G
1,
#900
0,
#910
b1000 F
1,
#920
0,
#930
b111 F
1,
#940
0,
#950
b110 F
1,
#960
0,
#970
b101 F
1,
#980
0,
#990
b100 F
1,
#1000
0,
#1010
b11 F
1,
#1020
0,
#1030
b10 F
1,
#1040
0,
#1050
b1 F
1,
#1060
0,
#1070
b100000000 *
b100000000 =
b100000000 I
1)
b0 F
1,
#1080
0,
#1090
0'
1$
13
b1000000010000001010001010011010110111101101110011010010111010001101111011100100010000000100000001000000010000000100000 2
0)
b1110 #
b1110 6
b0 !
b0 8
1"
b10 A
0J
1,
#1100
0,
#1110
0G
0$
07
00
1,
#1120
0,
#1130
03
17
0"
b1 :
b100 <
1,
1/
b1001 -
b1001 4
bz .
bz 5
#1140
0,
#1150
b111000000000 (
b111000000000 ?
b111000000000 E
1&
b1000000010000001010001010101110100001000100000001000000010000000100000001000000010000000100000001000000010000000100000 2
b100 A
1,
#1160
0,
#1170
1J
b1001 F
1H
1,
#1180
0,
#1190
b1000 F
1,
#1200
0,
#1210
b111 F
1,
#1220
0,
#1230
b110 F
1,
#1240
0,
#1250
b101 F
1,
#1260
0,
#1270
b100 F
1,
#1280
0,
#1290
b11 F
1,
#1300
0,
#1310
b10 F
1,
#1320
0,
#1330
b1 F
1,
#1340
0,
#1350
1)
b0 F
1,
#1360
0,
#1370
b100 +
b100 >
b100 D
0&
1'
b1000000010000001010001010001100110010101110100011000110110100000100000001000000010000000100000001000000010000000100000 2
0)
b1000 A
0J
1,
#1380
0,
#1390
1J
b1001 F
0H
1G
1,
#1400
0,
#1410
b1000 F
1,
#1420
0,
#1430
b111 F
1,
#1440
0,
#1450
b110 F
1,
#1460
0,
#1470
b101 F
1,
#1480
0,
#1490
b100 F
1,
#1500
0,
#1510
b11 F
1,
#1520
0,
#1530
b10 F
1,
#1540
0,
#1550
b1 F
1,
#1560
0,
#1570
b110100001000 *
b110100001000 =
b110100001000 I
1)
b0 F
1,
#1580
0,
#1590
0'
1$
0)
13
b1000000010000001010001010011010110111101101110011010010111010001101111011100100010000000100000001000000010000000100000 2
0J
b1101 #
b1101 6
b0 @
b1 !
b1 8
1"
b10 A
1,
#1600
0,
#1610
0G
0$
07
0/
1,
#1620
0,
#1630
1$
17
b1000 #
b1000 6
09
1,
1/
b1000 -
b1000 4
#1640
0,
#1650
0$
07
0/
1,
#1660
0,
#1670
03
0$
17
b0 !
b0 8
bx #
bx 6
b10 ;
1"
b0 :
b10 <
1,
b10001 .
b10001 5
10
b100 -
b100 4
#1680
0,
#1690
b10 +
b10 >
b10 D
1'
b1000000010000001010001010001100110010101110100011000110110100000100000001000000010000000100000001000000010000000100000 2
b1000 A
1,
#1700
0,
#1710
1J
b1001 F
1G
1,
#1720
0,
#1730
b1000 F
1,
#1740
0,
#1750
b111 F
1,
#1760
0,
#1770
b110 F
1,
#1780
0,
#1790
b101 F
1,
#1800
0,
#1810
b100 F
1,
#1820
0,
#1830
b11 F
1,
#1840
0,
#1850
b10 F
1,
#1860
0,
#1870
b1 F
1,
#1880
0,
#1890
b10100000100 *
b10100000100 =
b10100000100 I
1)
b0 F
1,
#1900
0,
#1910
0'
1$
13
0)
b1000000010000001010001010011010110111101101110011010010111010001101111011100100010000000100000001000000010000000100000 2
0J
b10001 #
b10001 6
b100 @
b101 B
b10 A
1,
#1920
0,
#1930
0G
0$
07
00
1,
#1940
0,
#1950
1$
17
b1 !
b1 8
b0 ;
b1101 #
b1101 6
19
1"
b1 :
b100 <
1,
1/
b1001 -
b1001 4
bz .
bz 5
#1960
0,
#1970
0$
03
b0 !
b0 8
0"
b101 #
b101 6
b10 ;
b110 <
b1101 -
b1101 4
1,
#1980
0,
#1990
b10100010001 (
b10100010001 ?
b10100010001 E
1&
b1000000010000001010001010101110100001000100000001000000010000000100000001000000010000000100000001000000010000000100000 2
b100 A
1,
#2000
0,
#2010
1J
b1001 F
1H
1,
#2020
0,
#2030
b1000 F
1,
#2040
0,
#2050
b111 F
1,
#2060
0,
#2070
b110 F
1,
#2080
0,
#2090
b101 F
1,
#2100
0,
#2110
b100 F
1,
#2120
0,
#2130
b11 F
1,
#2140
0,
#2150
b10 F
1,
#2160
0,
#2170
b1 F
1,
#2180
0,
#2190
1)
b0 F
1,
#2200
0,
#2210
b110 +
b110 >
b110 D
0&
1'
b1000000010000001010001010001100110010101110100011000110110100000100000001000000010000000100000001000000010000000100000 2
0)
b1000 A
0J
1,
#2220
0,
#2230
1J
b1001 F
0H
1G
1,
#2240
0,
#2250
b1000 F
1,
#2260
0,
#2270
b111 F
1,
#2280
0,
#2290
b110 F
1,
#2300
0,
#2310
b101 F
1,
#2320
0,
#2330
b100 F
1,
#2340
0,
#2350
b11 F
1,
#2360
0,
#2370
b10 F
1,
#2380
0,
#2390
b1 F
1,
#2400
0,
#2410
b110100001100 *
b110100001100 =
b110100001100 I
1)
b0 F
1,
#2420
0,
#2430
0'
1$
0)
13
b1000000010000001010001010011010110111101101110011010010111010001101111011100100010000000100000001000000010000000100000 2
0J
b1101 #
b1101 6
b0 @
b1 !
b1 8
1"
b10 A
1,
#2440
0,
#2450
0G
0$
07
0/
1,
